setup.py
distributions_JulyHerrera/Binomialdistribution.py
distributions_JulyHerrera/Gaussiandistribution.py
distributions_JulyHerrera/Generaldistribution.py
distributions_JulyHerrera/__init__.py
distributions_JulyHerrera.egg-info/PKG-INFO
distributions_JulyHerrera.egg-info/SOURCES.txt
distributions_JulyHerrera.egg-info/dependency_links.txt
distributions_JulyHerrera.egg-info/not-zip-safe
distributions_JulyHerrera.egg-info/top_level.txt